biosimulators_tellurium/__init__.py
biosimulators_tellurium/__main__.py
biosimulators_tellurium/_version.py
biosimulators_tellurium/config.py
biosimulators_tellurium/core.py
biosimulators_tellurium/data_model.py
biosimulators_tellurium-0.1.44.dist-info/LICENSE
biosimulators_tellurium-0.1.44.dist-info/METADATA
biosimulators_tellurium-0.1.44.dist-info/WHEEL
biosimulators_tellurium-0.1.44.dist-info/entry_points.txt
biosimulators_tellurium-0.1.44.dist-info/RECORD
