Metadata-Version: 2.1
Name: biosimulators-tellurium
Version: 0.1.44
Summary: BioSimulators-compliant command-line interface to the Tellurium/roadrunner simulator <https://tellurium.readthedocs.io/>.
Home-page: https://tellurium.readthedocs.io/en/latest/
License: MIT
Keywords: systems,biology,modeling,simulation
Author: Center for Reproducible Biomedical Modeling
Author-email: info@biosimulators.org
Requires-Python: >=3.10,<4.0
Classifier: Development Status :: 3 - Alpha
Classifier: Intended Audience :: Science/Research
Classifier: License :: OSI Approved :: MIT License
Classifier: Programming Language :: Python :: 3
Classifier: Programming Language :: Python :: 3.10
Classifier: Programming Language :: Python :: 3.11
Classifier: Programming Language :: Python :: 3.12
Classifier: Topic :: Scientific/Engineering :: Bio-Informatics
Requires-Dist: biosimulators_utils[logging,sbml] (>=0.2.3,<0.3.0)
Requires-Dist: docker (>=7.1.0,<8.0.0)
Requires-Dist: kisao (>=2.34,<3.0)
Requires-Dist: libroadrunner (>=2.7.0,<3.0.0)
Requires-Dist: lxml (>=4.9.2,<5.0.0)
Requires-Dist: numpy (>=1.24.4,<2.0.0)
Requires-Dist: pandas (>=2.0.2,<3.0.0)
Requires-Dist: pyPDF2 (>=3.0.1,<4.0.0)
Requires-Dist: tellurium (>=2.2.10,<3.0.0)
Project-URL: Repository, https://github.com/biosimulators/Biosimulators_tellurium
